histgrinder/HistObject.py
histgrinder/__init__.py
histgrinder/config.py
histgrinder/engine.py
histgrinder/example.py
histgrinder/interfaces.py
histgrinder/make_sample_file.py
histgrinder/transform.py
histgrinder/io/__init__.py
histgrinder/io/root.py
histgrinder-0.1.6.data/scripts/histgrinder
histgrinder-0.1.6.dist-info/LICENSE
histgrinder-0.1.6.dist-info/METADATA
histgrinder-0.1.6.dist-info/WHEEL
histgrinder-0.1.6.dist-info/top_level.txt
histgrinder-0.1.6.dist-info/RECORD
