Metadata-Version: 2.1
Name: histgrinder
Version: 0.1.6
Summary: Generic system to perform streaming transformations on histograms
Home-page: https://github.com/ponyisi/histogram_postprocessing
Author: Peter Onyisi
Author-email: ponyisi@utexas.edu
License: UNKNOWN
Platform: UNKNOWN
Classifier: Programming Language :: Python :: 3
Classifier: License :: OSI Approved :: Apache Software License
Classifier: Operating System :: OS Independent
Classifier: Topic :: Scientific/Engineering :: Physics
Requires-Python: >=3.6
License-File: LICENSE
Requires-Dist: PyYAML (>=5)
